setup.py
invoker/__init__.py
invoker/cmd.py
invoker/utils.py
invoker.egg-info/PKG-INFO
invoker.egg-info/SOURCES.txt
invoker.egg-info/dependency_links.txt
invoker.egg-info/entry_points.txt
invoker.egg-info/requires.txt
invoker.egg-info/top_level.txt
invoker/tests/__init__.py
invoker/tests/test_utils.py